spark_ai_cli/__init__.py
spark_ai_cli/cli.py
spark_ai_cli/pyspark_ai_utils.py
spark_ai_cli-0.1.0.dist-info/METADATA
spark_ai_cli-0.1.0.dist-info/WHEEL
spark_ai_cli-0.1.0.dist-info/entry_points.txt
spark_ai_cli-0.1.0.dist-info/RECORD
