Metadata-Version: 2.1
Name: spark-ai-cli
Version: 0.1.0
Summary: SparkAI on CLI
Author: Lucas Miranda
Author-email: lucas-m@outlook.com
Requires-Python: >=3.10,<4.0
Classifier: Programming Language :: Python :: 3
Classifier: Programming Language :: Python :: 3.10
Classifier: Programming Language :: Python :: 3.11
Requires-Dist: plotly (>=5.15.0,<6.0.0)
Requires-Dist: pyarrow (>=12.0.1,<13.0.0)
Requires-Dist: pyspark (>=3.4.1,<4.0.0)
Requires-Dist: pyspark-ai (>=0.1.8,<0.2.0)
Requires-Dist: typer (>=0.9.0,<0.10.0)
